PyFin/__init__.py
PyFin/Analysis/CrossSectionValueHolders.cp39-win_amd64.pyd
PyFin/Analysis/SecurityValueHolders.cp39-win_amd64.pyd
PyFin/Analysis/SeriesValues.cp39-win_amd64.pyd
PyFin/Analysis/__init__.py
PyFin/Analysis/transformer.cp39-win_amd64.pyd
PyFin/Analysis/DataProviders/DataProviders.py
PyFin/Analysis/DataProviders/__init__.py
PyFin/Analysis/TechnicalAnalysis/StatefulTechnicalAnalysers.cp39-win_amd64.pyd
PyFin/Analysis/TechnicalAnalysis/StatelessTechnicalAnalysers.cp39-win_amd64.pyd
PyFin/Analysis/TechnicalAnalysis/__init__.py
PyFin/CashFlows/CashFlow.py
PyFin/CashFlows/CashFlows.py
PyFin/CashFlows/FixedRateCoupon.py
PyFin/CashFlows/InterestRate.py
PyFin/CashFlows/__init__.py
PyFin/DateUtilities/Calendar.cp39-win_amd64.pyd
PyFin/DateUtilities/Date.cp39-win_amd64.pyd
PyFin/DateUtilities/DayCounter.py
PyFin/DateUtilities/Period.cp39-win_amd64.pyd
PyFin/DateUtilities/Schedule.cp39-win_amd64.pyd
PyFin/DateUtilities/__init__.py
PyFin/Enums/BizDayConventions.cp39-win_amd64.pyd
PyFin/Enums/Compoundings.py
PyFin/Enums/DateGeneration.cp39-win_amd64.pyd
PyFin/Enums/Factors.py
PyFin/Enums/Frequencies.py
PyFin/Enums/Months.cp39-win_amd64.pyd
PyFin/Enums/NormalizingType.cp39-win_amd64.pyd
PyFin/Enums/OptionType.cp39-win_amd64.pyd
PyFin/Enums/TimeUnits.cp39-win_amd64.pyd
PyFin/Enums/Weekdays.cp39-win_amd64.pyd
PyFin/Enums/__init__.py
PyFin/Env/Settings.py
PyFin/Env/__init__.py
PyFin/Math/ErrorFunction.cp39-win_amd64.pyd
PyFin/Math/MathConstants.cp39-win_amd64.pyd
PyFin/Math/__init__.py
PyFin/Math/udfs.cp39-win_amd64.pyd
PyFin/Math/Accumulators/IAccumulators.cp39-win_amd64.pyd
PyFin/Math/Accumulators/StatefulAccumulators.cp39-win_amd64.pyd
PyFin/Math/Accumulators/StatelessAccumulators.cp39-win_amd64.pyd
PyFin/Math/Accumulators/__init__.py
PyFin/Math/Accumulators/impl.cp39-win_amd64.pyd
PyFin/Math/Distributions/NormalDistribution.cp39-win_amd64.pyd
PyFin/Math/Distributions/__init__.py
PyFin/Math/Distributions/norm.cp39-win_amd64.pyd
PyFin/Math/RootFinder/Brent.py
Finance_Python-0.9.10.dist-info/LICENSE.txt
Finance_Python-0.9.10.dist-info/METADATA
Finance_Python-0.9.10.dist-info/WHEEL
Finance_Python-0.9.10.dist-info/top_level.txt
Finance_Python-0.9.10.dist-info/RECORD
