Metadata-Version: 2.1
Name: Finance-Python
Version: 0.9.10
Summary: PyFin 0.9.10
Home-page: https://github.com/ChinaQuants/Finance-Python
Author: cheng li
Author-email: wegamekinglc@hotmail.com
License-File: LICENSE.txt
Requires-Dist: cython (>=0.26.0)
Requires-Dist: numpy (>=1.10.1)
Requires-Dist: pandas (>=0.18.0)
Requires-Dist: scipy (>=0.18.0)
Requires-Dist: simpleutils (>=0.1.0)
Requires-Dist: six (>=1.10.0)
